alternative_lib/__init__.py
alternative_lib/alternative_client.py
alternative_eu_lib-0.2.1.dist-info/LICENSE
alternative_eu_lib-0.2.1.dist-info/METADATA
alternative_eu_lib-0.2.1.dist-info/WHEEL
alternative_eu_lib-0.2.1.dist-info/top_level.txt
alternative_eu_lib-0.2.1.dist-info/RECORD
